roura_agent/__init__.py
roura_agent/branding.py
roura_agent/cli.py
roura_agent/config.py
roura_agent/constants.py
roura_agent/errors.py
roura_agent/licensing.py
roura_agent/logging.py
roura_agent/metrics.py
roura_agent/ollama.py
roura_agent/onboarding.py
roura_agent/patch.py
roura_agent/plugins.py
roura_agent/prompt.py
roura_agent/retry.py
roura_agent/safety.py
roura_agent/secrets.py
roura_agent/server.py
roura_agent/session.py
roura_agent/shutdown.py
roura_agent/stream.py
roura_agent/update.py
roura_agent/agent/__init__.py
roura_agent/agent/context.py
roura_agent/agent/loop.py
roura_agent/agent/planner.py
roura_agent/agent/summarizer.py
roura_agent/agents/__init__.py
roura_agent/agents/agent_loop.py
roura_agent/agents/approval.py
roura_agent/agents/base.py
roura_agent/agents/constraints.py
roura_agent/agents/context.py
roura_agent/agents/cursor_bridge.py
roura_agent/agents/executor.py
roura_agent/agents/integrations.py
roura_agent/agents/messaging.py
roura_agent/agents/orchestrator.py
roura_agent/agents/parallel.py
roura_agent/agents/registry.py
roura_agent/agents/specialized.py
roura_agent/llm/__init__.py
roura_agent/llm/anthropic.py
roura_agent/llm/base.py
roura_agent/llm/ollama.py
roura_agent/llm/openai.py
roura_agent/memory/__init__.py
roura_agent/memory/consent.py
roura_agent/memory/encryption.py
roura_agent/memory/persistent.py
roura_agent/memory/project.py
roura_agent/plugins/__init__.py
roura_agent/plugins/base.py
roura_agent/plugins/loader.py
roura_agent/plugins/logging.py
roura_agent/plugins/manager.py
roura_agent/plugins/mcp.py
roura_agent/plugins/permissions.py
roura_agent/plugins/registry.py
roura_agent/plugins/sandbox.py
roura_agent/pro/__init__.py
roura_agent/pro/automation.py
roura_agent/pro/billing.py
roura_agent/pro/ci.py
roura_agent/pro/quotas.py
roura_agent/tools/__init__.py
roura_agent/tools/base.py
roura_agent/tools/build.py
roura_agent/tools/doctor.py
roura_agent/tools/fs.py
roura_agent/tools/git.py
roura_agent/tools/github.py
roura_agent-4.1.2.dist-info/METADATA
roura_agent-4.1.2.dist-info/WHEEL
roura_agent-4.1.2.dist-info/entry_points.txt
roura_agent-4.1.2.dist-info/top_level.txt
roura_agent-4.1.2.dist-info/RECORD
