Metadata-Version: 2.4
Name: roura-agent
Version: 4.1.2
Summary: Local-first AI coding assistant powered by Ollama, OpenAI, or Anthropic
License: MIT
Project-URL: Homepage, https://github.com/roura-io/roura-agent
Project-URL: Documentation, https://docs.roura.io
Project-URL: Repository, https://github.com/roura-io/roura-agent
Project-URL: Issues, https://github.com/roura-io/roura-agent/issues
Keywords: ai,coding,assistant,llm,ollama,openai,claude,cli
Classifier: Development Status :: 4 - Beta
Classifier: Environment :: Console
Classifier: Intended Audience :: Developers
Classifier: License :: OSI Approved :: MIT License
Classifier: Programming Language :: Python :: 3
Classifier: Programming Language :: Python :: 3.9
Classifier: Programming Language :: Python :: 3.10
Classifier: Programming Language :: Python :: 3.11
Classifier: Programming Language :: Python :: 3.12
Classifier: Topic :: Software Development
Classifier: Topic :: Software Development :: Code Generators
Requires-Python: >=3.9
Requires-Dist: typer>=0.12.0
Requires-Dist: rich>=13.7.0
Requires-Dist: httpx>=0.27.0
Requires-Dist: pydantic>=2.7.0
Requires-Dist: python-dotenv>=1.0.1
Requires-Dist: prompt_toolkit>=3.0.0
Provides-Extra: dev
Requires-Dist: pytest>=8.0.0; extra == "dev"
Requires-Dist: pytest-cov>=4.1.0; extra == "dev"
Requires-Dist: ruff>=0.4.0; extra == "dev"
Requires-Dist: pyright>=1.1.350; extra == "dev"
Provides-Extra: tui
Requires-Dist: textual>=0.50.0; extra == "tui"
Provides-Extra: server
Requires-Dist: fastapi>=0.109.0; extra == "server"
Requires-Dist: uvicorn>=0.27.0; extra == "server"
Requires-Dist: python-multipart>=0.0.6; extra == "server"
Provides-Extra: crypto
Requires-Dist: cryptography>=42.0.0; extra == "crypto"
